routers/__init__.py
routers/test.py
ikamai_pegasus-0.0.1.dist-info/METADATA
ikamai_pegasus-0.0.1.dist-info/WHEEL
ikamai_pegasus-0.0.1.dist-info/top_level.txt
ikamai_pegasus-0.0.1.dist-info/RECORD
