Metadata-Version: 2.1
Name: ikamai-pegasus
Version: 0.0.1
Summary: A Pubsub
Home-page: https://github.com/rizoadev/pegasus
Author: Riza Masykur
Author-email: hanirizo@gmail.com
Project-URL: Bug Tracker, https://github.com/rizoadev/pegasus/issues
Classifier: Programming Language :: Python :: 3
Classifier: License :: OSI Approved :: MIT License
Classifier: Operating System :: OS Independent
Requires-Python: >=3.6
